MANIFEST.in
README.rst
setup.py
docs/HISTORY.txt
docs/LICENSE.GPL
docs/LICENSE.txt
ftw/__init__.py
ftw.tagging.egg-info/PKG-INFO
ftw.tagging.egg-info/SOURCES.txt
ftw.tagging.egg-info/dependency_links.txt
ftw.tagging.egg-info/entry_points.txt
ftw.tagging.egg-info/namespace_packages.txt
ftw.tagging.egg-info/not-zip-safe
ftw.tagging.egg-info/requires.txt
ftw.tagging.egg-info/top_level.txt
ftw/tagging/__init__.py
ftw/tagging/behavior.py
ftw/tagging/config.py
ftw/tagging/configure.zcml
ftw/tagging/indexer.py
ftw/tagging/setuphandlers.py
ftw/tagging/testing.py
ftw/tagging/utils.py
ftw/tagging/vocabularies.py
ftw/tagging/Extensions/install.py
ftw/tagging/browser/__init__.py
ftw/tagging/browser/configure.zcml
ftw/tagging/browser/interfaces.py
ftw/tagging/browser/stylesheets/main.css
ftw/tagging/browser/stylesheets/tagcloud.css
ftw/tagging/browser/stylesheets/tagging-compiled.css
ftw/tagging/browser/viewlets/__init__.py
ftw/tagging/browser/viewlets/taglist.pt
ftw/tagging/browser/viewlets/taglist.py
ftw/tagging/browser/views/__init__.py
ftw/tagging/browser/views/objects_by_tag.pt
ftw/tagging/browser/views/objects_by_tag.py
ftw/tagging/interfaces/__init__.py
ftw/tagging/interfaces/tagging.py
ftw/tagging/locales/ftw.tagging.pot
ftw/tagging/locales/de/LC_MESSAGES/ftw.tagging.po
ftw/tagging/locales/en/LC_MESSAGES/ftw.tagging.po
ftw/tagging/locales/es/LC_MESSAGES/ftw.tagging.po
ftw/tagging/locales/fr/LC_MESSAGES/ftw.tagging.po
ftw/tagging/portlets/__init__.py
ftw/tagging/portlets/configure.zcml
ftw/tagging/portlets/tags.pt
ftw/tagging/portlets/tags.py
ftw/tagging/portlets/tags_plone5.pt
ftw/tagging/profiles/default/browserlayer.xml
ftw/tagging/profiles/default/catalog.xml
ftw/tagging/profiles/default/cssregistry.xml
ftw/tagging/profiles/default/metadata.xml
ftw/tagging/profiles/default/portlets.xml
ftw/tagging/profiles/default/skins.xml
ftw/tagging/profiles/default/viewlets.xml
ftw/tagging/profiles/default_plone5/browserlayer.xml
ftw/tagging/profiles/default_plone5/catalog.xml
ftw/tagging/profiles/default_plone5/metadata.xml
ftw/tagging/profiles/default_plone5/portlets.xml
ftw/tagging/profiles/default_plone5/registry.xml
ftw/tagging/profiles/default_plone5/skins.xml
ftw/tagging/profiles/default_plone5/viewlets.xml
