Metadata-Version: 2.1
Name: ftw.tagging
Version: 2.0.1
Summary: Tagging add-on for Plone
Home-page: https://github.com/4teamwork/ftw.tagging
Author: 4teamwork AG
Author-email: mailto:info@4teamwork.ch
Maintainer: Mathias Leimgruber
License: GPL2
Keywords: ftw tagging plone
Platform: UNKNOWN
Classifier: Framework :: Plone
Classifier: Framework :: Plone :: 4.3
Classifier: Framework :: Plone :: 5.1
Classifier: Programming Language :: Python
Classifier: Topic :: Software Development :: Libraries :: Python Modules
Provides-Extra: tests
